add.py
sub.py
alteredcarbon-0.1.dist-info/METADATA
alteredcarbon-0.1.dist-info/WHEEL
alteredcarbon-0.1.dist-info/top_level.txt
alteredcarbon-0.1.dist-info/RECORD
