Metadata-Version: 2.1
Name: alteredcarbon
Version: 0.1
Summary: A library for performing addition and subtraction
Home-page: https://github.com/cumbersomeamir
Author: Amir Kidwai
Author-email: findamirkidwai@gmail.com
License: UNKNOWN
Platform: UNKNOWN
